{
  "id": "task_1772826905959_xonp",
  "name": "runtime-audit",
  "description": "Auto-created from event evt_mmfb6rc1_l0z67q",
  "source_event": "evt_mmfb6rc1_l0z67q",
  "source_type": "dto.task.created",
  "status": "pending",
  "created_at": "2026-03-06T19:55:05.959Z",
  "payload": {
    "task_id": "task_1772826605281_q1b6",
    "name": "runtime-audit",
    "source_event": "evt_mmfb0cl3_bg6481",
    "model": "zhipu/glm-5"
  },
  "model": "zhipu/glm-5",
  "updated_at": "2026-03-06T20:00:02.682Z"
}
