{
  "recordId": "evo-9024f8476971",
  "skillId": "unknown",
  "skillName": "unknown",
  "timestamp": 1772509979313,
  "trigger": "event-bridge:seef.skill.validated",
  "status": "unknown",
  "metrics": {
    "evaluation": {
      "score": 0,
      "issuesFound": 0,
      "criticalIssues": 0
    },
    "optimization": {
      "filesModified": 0,
      "issuesFixed": 0,
      "operationsCompleted": 0
    },
    "validation": {
      "passed": false,
      "testsRun": 0,
      "testsPassed": 0
    }
  },
  "changes": {
    "total": 0,
    "byType": {
      "added": 0,
      "modified": 0,
      "deleted": 0
    },
    "details": []
  },
  "stages": {
    "evaluation": {
      "completed": false
    },
    "optimization": {
      "completed": false
    },
    "validation": {
      "completed": false
    }
  },
  "metadata": {
    "recorderVersion": "1.0.0",
    "recordedAt": 1772509979313
  }
}